_ZcurvePy.cpython-310-x86_64-linux-gnu.so
ZcurvePy/Util.py
ZcurvePy/__init__.py
ZcurvePy/Scripts/RunZcurveEncoder.py
ZcurvePy/Scripts/RunZcurvePlotter.py
ZcurvePy/Scripts/RunZcurvePlotter3D.py
ZcurvePy/Scripts/RunZcurveSegmenter.py
ZcurvePy/assets/config/config.ini
ZcurvePy/assets/image/icon.ico
ZcurvePy/include/ZcurvePy.cpp
ZcurvePy/include/ZcurvePyAPIs.cpp
ZcurvePy/include/ZcurvePyAPIs.h
ZcurvePy/include/ZcurvePyCore.cpp
ZcurvePy/include/ZcurvePyCore.h
ZcurvePy/include/ZcurvePyUtil.cpp
ZcurvePy/include/ZcurvePyUtil.h
zcurvepy-1.7.0.dist-info/licenses/LICENSE
zcurvepy-1.7.0.dist-info/METADATA
zcurvepy-1.7.0.dist-info/WHEEL
zcurvepy-1.7.0.dist-info/entry_points.txt
zcurvepy-1.7.0.dist-info/top_level.txt
zcurvepy-1.7.0.dist-info/RECORD
