Metadata-Version: 2.1
Name: zcurvepy
Version: 1.7.0
Summary: High performance Python toolkit for the Z-curve theory
Home-page: https://zcurvehub-docs.readthedocs.io/
Author: TUBIC
Author-email: fgao@tju.edu.cn
Maintainer: Zetong Zhang
Maintainer-email: zhangzetong@tju.edu.cn
License: MIT License
Requires-Dist: matplotlib
Requires-Dist: biopython ==1.84
Requires-Dist: scikit-learn ==1.6.1
Requires-Dist: numpy <2.0.0
